[
  {
    "id": "song_001",
    "title": "Neon Nights",
    "artist": "Rizz Originals",
    "album": "Cloud Sessions",
    "audioPath": "music/rizz-originals/neon-nights.mp3",
    "imagePath": "covers/rizz-originals/neon-nights.jpg",
    "durationSeconds": 207
  },
  {
    "id": "song_002",
    "title": "Morning Drive",
    "artist": "Rizz Originals",
    "album": "Cloud Sessions",
    "audioPath": "music/rizz-originals/morning-drive.mp3",
    "imagePath": "covers/rizz-originals/morning-drive.jpg",
    "durationSeconds": 188
  }
]
